LICENSE
MANIFEST.in
README.rst
requirements.txt
setup.py
pyupyun.egg-info/PKG-INFO
pyupyun.egg-info/SOURCES.txt
pyupyun.egg-info/dependency_links.txt
pyupyun.egg-info/requires.txt
pyupyun.egg-info/top_level.txt
test/test_upyun.py
test/asset/upyun-test.gif
test/asset/upyun-test.txt
upyun/__init__.py
upyun/auth.py
upyun/const.py
upyun/response.py