Metadata-Version: 1.1
Name: pyupyun
Version: 0.1
Summary: Feature complete upyun REST client
Home-page: https://github.com/kols/upyun
Author: Kane Dou
Author-email: douqilong@gmail.com
License: Licensed under the Apache License, Version 2.0 (the "License");
